llmux/interfaces/tui.py
llmux-0.2.4.dist-info/LICENSE
llmux-0.2.4.dist-info/METADATA
llmux-0.2.4.dist-info/WHEEL
llmux-0.2.4.dist-info/entry_points.txt
llmux-0.2.4.dist-info/RECORD
