Metadata-Version: 2.3
Name: llmux
Version: 0.2.4
Summary: LLM inference for power users.
Author: Daniel Souza
Requires-Python: >=3.12,<4.0
Classifier: Programming Language :: Python :: 3
Classifier: Programming Language :: Python :: 3.12
Classifier: Programming Language :: Python :: 3.13
Requires-Dist: PyYAML (>=6.0,<7.0)
Requires-Dist: Pygments (>=2.14,<3.0)
Requires-Dist: certifi (>=2022.12.7,<2023.0.0)
Requires-Dist: charset-normalizer (>=3.1,<4.0)
Requires-Dist: click (>=8.1,<9.0)
Requires-Dist: idna (>=3.4,<4.0)
Requires-Dist: markdown-it-py (>=2.2,<3.0)
Requires-Dist: mdurl (>=0.1,<0.2)
Requires-Dist: mypy-extensions (>=1.0,<2.0)
Requires-Dist: packaging (>=23.0,<24.0)
Requires-Dist: pathspec (>=0.11,<0.12)
Requires-Dist: platformdirs (>=3.1,<4.0)
Requires-Dist: prompt-toolkit (>=3.0,<4.0)
Requires-Dist: requests (>=2.28,<3.0)
Requires-Dist: rich (>=13.4,<14.0)
Requires-Dist: tomli (>=2.0,<3.0)
Requires-Dist: typing_extensions (>=4.6,<5.0)
Requires-Dist: urllib3 (>=1.26,<2.0)
Requires-Dist: wcwidth (>=0.2,<0.3)
Project-URL: Homepage, https://github.com/danisztls/llmux
